LegendWCF/__init__.py
LegendWCF/data/__init__.py
LegendWCF/data/json_.py
LegendWCF/data/yaml_.py
LegendWCF/dfa/DFA.py
LegendWCF/dfa/__init__.py
LegendWCF/dfa/ban.txt
LegendWCF/job/__init__.py
LegendWCF/job/job_mgmt.py
LegendWCF/msg/__init__.py
LegendWCF/msg/jieba_.py
LegendWCF/msg/utils.py
LegendWCF/wcf/__init__.py
LegendWCF/wcf/log.py
LegendWCF/wcf/logging.yaml
LegendWCF/wcf/semaphore.py
LegendWCF/wcf/sendMsg.py
LegendWCF/wcf/to_half.py
LegendWCF-1.4.2.dist-info/LICENSE
LegendWCF-1.4.2.dist-info/METADATA
LegendWCF-1.4.2.dist-info/WHEEL
LegendWCF-1.4.2.dist-info/top_level.txt
LegendWCF-1.4.2.dist-info/RECORD
