Metadata-Version: 2.1
Name: LegendWCF
Version: 1.4.2
Summary: 对于微信机器人编码体验的提升以及对WCFerry接口的优化
Home-page: https://github.com/kanwuqing/LegendWCF
Author: kanwuqing
Author-email: kanwuqing@163.com
License: MPL License
Platform: all
Classifier: Intended Audience :: Developers
Classifier: Operating System :: OS Independent
Classifier: Natural Language :: Chinese (Simplified)
Classifier: Programming Language :: Python
Classifier: Programming Language :: Python :: 2
Classifier: Programming Language :: Python :: 2.7
Classifier: Programming Language :: Python :: 3
Classifier: Programming Language :: Python :: 3.5
Classifier: Programming Language :: Python :: 3.6
Classifier: Programming Language :: Python :: 3.7
Classifier: Programming Language :: Python :: 3.8
Classifier: Programming Language :: Python :: 3.9
Classifier: Programming Language :: Python :: 3.10
Classifier: Programming Language :: Python :: 3.11
Classifier: Programming Language :: Python :: 3.12
Classifier: Topic :: Software Development :: Libraries
License-File: LICENSE
Requires-Dist: orjson>=3.10.15
Requires-Dist: PyYAML>=6.0.2
Requires-Dist: APScheduler>=3.11.0
Requires-Dist: jieba>=0.42.1
Requires-Dist: wcferry>=39.0.14
